README.md
setup.cfg
setup.py
console_testing/BasicConsole.py
console_testing/Console.py
console_testing/ConsoleExpectation.py
console_testing/MockConsole.py
console_testing/__init__.py
console_testing.egg-info/PKG-INFO
console_testing.egg-info/SOURCES.txt
console_testing.egg-info/dependency_links.txt
console_testing.egg-info/entry_points.txt
console_testing.egg-info/top_level.txt